sitfproject/__init__.py
sitfproject/fileinfo.py
sitfproject/progressbar.py
sitfproject/sitf.py
sitf-1.2.1.dist-info/METADATA
sitf-1.2.1.dist-info/WHEEL
sitf-1.2.1.dist-info/entry_points.txt
sitf-1.2.1.dist-info/top_level.txt
sitf-1.2.1.dist-info/RECORD
