Metadata-Version: 2.1
Name: sitf
Version: 1.2.1
Summary: Sort Images by day's wise into to the folders
Home-page: UNKNOWN
Author: Shatak Gurukar
Author-email: shatakgurukar@gmail.com
License: BSD License
Keywords: folders files sorter images
Platform: UNKNOWN
Classifier: Development Status :: 4 - Beta
Classifier: Intended Audience :: End Users/Desktop
Classifier: License :: OSI Approved :: BSD License
Classifier: Programming Language :: Python :: 3.6
Classifier: Programming Language :: Python :: 3.7
Classifier: Programming Language :: Python :: 3.8
Classifier: Programming Language :: Python :: 3.9
Requires-Python: >=3.6
Requires-Dist: Pillow
